physutils/__init__.py
physutils/_version.py
physutils/io.py
physutils/physio.py
physutils/tasks.py
physutils/utils.py
physutils/tests/__init__.py
physutils/tests/conftest.py
physutils/tests/test_io.py
physutils/tests/test_physio.py
physutils/tests/test_tasks.py
physutils/tests/utils.py
physutils-0.3.0.dist-info/LICENSE
physutils-0.3.0.dist-info/METADATA
physutils-0.3.0.dist-info/WHEEL
physutils-0.3.0.dist-info/top_level.txt
physutils-0.3.0.dist-info/RECORD
