Metadata-Version: 2.1
Name: physutils
Version: 0.3.0
Summary: Set of utilities meant to be used with Physiopy libraries
Home-page: https://github.com/physiopy/physutils
Download-URL: https://github.com/physiopy/physutils
Author: The Physiopy Community
Maintainer: The Physiopy Community
Maintainer-email: physiopy.community@gmail.com
License: Apache-2.0
Platform: OS Independent
Classifier: Development Status :: 3 - Alpha
Classifier: Intended Audience :: Science/Research
Classifier: License :: OSI Approved :: Apache Software License
Classifier: Programming Language :: Python :: 3
Provides: physutils
Requires-Python: >=3.6.1
License-File: LICENSE
Requires-Dist: matplotlib
Requires-Dist: numpy>=1.9.3
Requires-Dist: loguru
Provides-Extra: bids
Requires-Dist: pybids; extra == "bids"
Provides-Extra: dev
Requires-Dist: sphinx>=2.0; extra == "dev"
Requires-Dist: sphinx-argparse; extra == "dev"
Requires-Dist: sphinx-rtd-theme; extra == "dev"
Requires-Dist: flake8>=3.7; extra == "dev"
Requires-Dist: flake8-docstrings>=1.5; extra == "dev"
Requires-Dist: black; extra == "dev"
Requires-Dist: isort<6.0.0; extra == "dev"
Requires-Dist: pydocstyle; extra == "dev"
Requires-Dist: codespell; extra == "dev"
Requires-Dist: scipy; extra == "dev"
Requires-Dist: pytest>=5.3; extra == "dev"
Requires-Dist: pytest-cov; extra == "dev"
Requires-Dist: pydra; extra == "dev"
Requires-Dist: pybids; extra == "dev"
Requires-Dist: pre-commit; extra == "dev"
Provides-Extra: devtools
Requires-Dist: pre-commit; extra == "devtools"
Provides-Extra: doc
Requires-Dist: sphinx>=2.0; extra == "doc"
Requires-Dist: sphinx-argparse; extra == "doc"
Requires-Dist: sphinx-rtd-theme; extra == "doc"
Provides-Extra: pydra
Requires-Dist: pydra; extra == "pydra"
Provides-Extra: style
Requires-Dist: flake8>=3.7; extra == "style"
Requires-Dist: flake8-docstrings>=1.5; extra == "style"
Requires-Dist: black; extra == "style"
Requires-Dist: isort<6.0.0; extra == "style"
Requires-Dist: pydocstyle; extra == "style"
Requires-Dist: codespell; extra == "style"
Provides-Extra: test
Requires-Dist: scipy; extra == "test"
Requires-Dist: pytest>=5.3; extra == "test"
Requires-Dist: pytest-cov; extra == "test"
Requires-Dist: pydra; extra == "test"
Requires-Dist: pybids; extra == "test"
Requires-Dist: flake8>=3.7; extra == "test"
Requires-Dist: flake8-docstrings>=1.5; extra == "test"
Requires-Dist: black; extra == "test"
Requires-Dist: isort<6.0.0; extra == "test"
Requires-Dist: pydocstyle; extra == "test"
Requires-Dist: codespell; extra == "test"
